leja_recharge_sdk/__init__.py
leja_recharge_sdk/client.py
leja_recharge_sdk/exceptions.py
leja_recharge_sdk/models.py
leja_recharge_sdk-0.1.6.dist-info/LICENSE.md
leja_recharge_sdk-0.1.6.dist-info/METADATA
leja_recharge_sdk-0.1.6.dist-info/WHEEL
leja_recharge_sdk-0.1.6.dist-info/RECORD
