Metadata-Version: 2.3
Name: leja-recharge-sdk
Version: 0.1.6
Summary: Python SDK for Leja Recharge API
Author: Leja
Author-email: contact@leja.co.ke
Requires-Python: >=3.8,<4.0
Classifier: Programming Language :: Python :: 3
Classifier: Programming Language :: Python :: 3.8
Classifier: Programming Language :: Python :: 3.9
Classifier: Programming Language :: Python :: 3.10
Classifier: Programming Language :: Python :: 3.11
Classifier: Programming Language :: Python :: 3.12
Classifier: Programming Language :: Python :: 3.13
Requires-Dist: httpx (>=0.26.0,<0.27.0)
Requires-Dist: pydantic (>=2.6.1,<3.0.0)
Requires-Dist: python-dotenv (>=1.0.0,<2.0.0)
Project-URL: Bug Tracker, https://github.com/Asilimia/leja-recharge-python-sdk/issues
Project-URL: Homepage, https://github.com/Asilimia/leja-recharge-python-sdk
